LICENSE.txt
README.rst
setup.py
src/mv_oci_sdk.egg-info/PKG-INFO
src/mv_oci_sdk.egg-info/SOURCES.txt
src/mv_oci_sdk.egg-info/dependency_links.txt
src/mv_oci_sdk.egg-info/requires.txt
src/mv_oci_sdk.egg-info/top_level.txt
src/oci/__init__.py
src/oci/alloy.py
src/oci/base_client.py
src/oci/config.py
src/oci/constants.py
src/oci/decorators.py
src/oci/exceptions.py
src/oci/fips.py
src/oci/regions.py
src/oci/regions_definitions.py
src/oci/request.py
src/oci/response.py
src/oci/service_endpoints.py
src/oci/signer.py
src/oci/util.py
src/oci/version.py
src/oci/waiter.py
src/oci/_vendor/__init__.py
src/oci/_vendor/six.py
src/oci/_vendor/chardet/__init__.py
src/oci/_vendor/chardet/big5freq.py
src/oci/_vendor/chardet/big5prober.py
src/oci/_vendor/chardet/chardistribution.py
src/oci/_vendor/chardet/charsetgroupprober.py
src/oci/_vendor/chardet/charsetprober.py
src/oci/_vendor/chardet/codingstatemachine.py
src/oci/_vendor/chardet/compat.py
src/oci/_vendor/chardet/cp949prober.py
src/oci/_vendor/chardet/enums.py
src/oci/_vendor/chardet/escprober.py
src/oci/_vendor/chardet/escsm.py
src/oci/_vendor/chardet/eucjpprober.py
src/oci/_vendor/chardet/euckrfreq.py
src/oci/_vendor/chardet/euckrprober.py
src/oci/_vendor/chardet/euctwfreq.py
src/oci/_vendor/chardet/euctwprober.py
src/oci/_vendor/chardet/gb2312freq.py
src/oci/_vendor/chardet/gb2312prober.py
src/oci/_vendor/chardet/hebrewprober.py
src/oci/_vendor/chardet/jisfreq.py
src/oci/_vendor/chardet/jpcntx.py
src/oci/_vendor/chardet/langbulgarianmodel.py
src/oci/_vendor/chardet/langgreekmodel.py
src/oci/_vendor/chardet/langhebrewmodel.py
src/oci/_vendor/chardet/langhungarianmodel.py
src/oci/_vendor/chardet/langrussianmodel.py
src/oci/_vendor/chardet/langthaimodel.py
src/oci/_vendor/chardet/langturkishmodel.py
src/oci/_vendor/chardet/latin1prober.py
src/oci/_vendor/chardet/mbcharsetprober.py
src/oci/_vendor/chardet/mbcsgroupprober.py
src/oci/_vendor/chardet/mbcssm.py
src/oci/_vendor/chardet/sbcharsetprober.py
src/oci/_vendor/chardet/sbcsgroupprober.py
src/oci/_vendor/chardet/sjisprober.py
src/oci/_vendor/chardet/universaldetector.py
src/oci/_vendor/chardet/utf8prober.py
src/oci/_vendor/chardet/version.py
