Metadata-Version: 2.4
Name: mv_oci_sdk
Version: 2.142.0.10
Summary: Oracle Cloud Infrastructure Python SDK modified by Moviri for use in Dynatrace extensions
Home-page: https://github.com/Moviri/mv-oci-sdk
Author: Moviri
Author-email: dynatrace_extensions@moviri.com
License: Universal Permissive License 1.0 or Apache License 2.0
Classifier: Development Status :: 5 - Production/Stable
Classifier: Intended Audience :: Developers
Classifier: License :: OSI Approved :: Apache Software License
Classifier: License :: OSI Approved :: Universal Permissive License (UPL)
Classifier: Programming Language :: Python :: 3.6
Classifier: Programming Language :: Python :: 3.7
Classifier: Programming Language :: Python :: 3.8
Classifier: Programming Language :: Python :: 3.9
License-File: LICENSE.txt
Requires-Dist: certifi
Requires-Dist: configparser==4.0.2; python_version < "3"
Requires-Dist: cryptography<46.0.0,>=3.2.1
Requires-Dist: pyOpenSSL<25.0.0,>=17.5.0
Requires-Dist: python-dateutil<3.0.0,>=2.5.3
Requires-Dist: pytz>=2016.10
Requires-Dist: circuitbreaker<2.0.0,>=1.3.1; python_version <= "3.6"
Requires-Dist: circuitbreaker<3.0.0,>=1.3.1; python_version >= "3.7"
Dynamic: author
Dynamic: author-email
Dynamic: classifier
Dynamic: description
Dynamic: home-page
Dynamic: license
Dynamic: license-file
Dynamic: requires-dist
Dynamic: summary
